{
  "page": "Discovering Infrastructure",
  "stages": [
    {
      "content": "this is one page, a collection is made up of millions of these units. In the 2016-17 financial year, the contractors digitising SLNSW’s DSM collection digitised ~600,000 pages"
    },
    {
      "content": "this is the amount of care going into a single page of text (and pictorial content has even higher standards)"
    },
    {
      "content": "to support, store, and maintain these pages, all these other moving parts come into play"
    }
  ]
}
